rppxml.cpython-312-darwin.so
rppxml-0.1.1.dist-info/METADATA
rppxml-0.1.1.dist-info/WHEEL
rppxml-0.1.1.dist-info/top_level.txt
rppxml-0.1.1.dist-info/RECORD
